setup.py
captcha/__init__.py
captcha/captcha.py
get_captcha.egg-info/PKG-INFO
get_captcha.egg-info/SOURCES.txt
get_captcha.egg-info/dependency_links.txt
get_captcha.egg-info/not-zip-safe
get_captcha.egg-info/requires.txt
get_captcha.egg-info/top_level.txt