Metadata-Version: 1.0
Name: get-captcha
Version: 0.2.0
Summary: Get Captcha text from the image using real intelligence, not artificial intelligence. Its a client for get-captcha apis
Home-page: https://github.com/suraj-arya/captcha
Author: Suraj Arya
Author-email: suraj@loanzen.in
License: UNKNOWN
Platform: UNKNOWN
